{
  "{[DamageTable.Firestaff_Pillar.DmgCoef * 100]}":	"120",
  "{[ManaCosts_Player.44.ManaCost]}":	"15",
  "{[FireMagicAbilityTable.Upgrade_Firestaff_PillarofFire_Dmg.BaseDamage * 100]}":	"40",
  "{[FireMagicAbilityTable.Upgrade_Firestaff_PillarofFire_Mana.Mana * 100]}":	"10",
  "{[DamageTable.FireStaff_Storm.DmgCoef * 100]}":	"20",
  "{[ManaCosts_Player.45.ManaCost / 6]}": 	"6",
  "{[ManaCosts_Player.45.ManaCost]}": 	"35",
  "{[FireMagicAbilityTable.Upgrade_Firestaff_MeteorShower_Mana.Mana * 100]}": "1",
  "{[DamageTable.Firestaff_Siege_AOE.DmgCoef * 100]}":	"200",
  "{[StatusEffects.Status_FireStaff_ScorchedEarth_DOT.HealthModifierDamageBased * -100]}":	"10",
  "{[ManaCosts_Player.48.ManaCost]}": 	"25",
  "{[FireMagicAbilityTable.Upgrade_Firestaff_Fireball_Mana.Mana * 100]}":	"10",
  "{[FireMagicAbilityTable.Upgrade_Firestaff_Fireball_Mana.CooldownTimer * -100]}":	"7",
  "{[FireMagicAbilityTable.Passive_Firestaff_FireMage_ManaOnHit.Mana * 100]}":	"5",
  "{[FireMagicAbilityTable.Passive_Firestaff_FireMage_CDRHeavy.CooldownTimer * 100]}":	"10",
  "{[StatusEffects.Status_Passive_Firestaff_FireMage_DmgFullMana.DMGStandard * 100]}":	"10",
  "{[StatusEffects.FireStaff_Pyro_DOT.BaseDuration]}":	"6",
  "{[FireMagicAbilityTable.Passive_Firestaff_FireMage_Crit.CritChance * 100]}":	"15",
  "{[StatusEffects.Status_Passive_Firestaff_FireMage_DmgNoDmg_Timer.BaseDuration]}":	"3",
  "{[StatusEffects.Status_Passive_Firestaff_FireMage_DmgNoDmg.DMGStandard * 100]}":	"10",
  "{[FireMagicAbilityTable.Passive_Firestaff_FireMage_CritDmg.CritDamage * 100]}":	"35",
  "{[StatusEffects.Status_Ultimate_Firemage_DMG.DMGStandard * 100]}":	"30",
  "{[StatusEffects.Status_Ultimate_Firemage.BaseDuration]}":	"7",
  "{[StatusEffects.Status_Ultimate_Firemage_Timer.BaseDuration]}":	"30",
  "{[DamageTable.Firestaff_Incinerate.DmgCoef * 100]}":	"125",
  "{[DamageTable.Firestaff_Incinerate.ImpactDistanceY]}":	"2",
  "{[ManaCosts_Player.42.ManaCost]}":	"25",
  "{[FireMagicAbilityTable.Upgrade_Firestaff_Incinerate_Heal.DmgPctToHealth * 100]}":	"30",
  "{[DamageTable.FireStaff_FlameThrower.DmgCoef * 100]}":	"25",
  "{[StatusEffects.FireStaff_Pyro_DOT.HealthModifierDamageBased * -100]}":"3",
  "{[ManaCosts_Player.43.ManaCost * 2]}":	"4",
  "{[FireMagicAbilityTable.Upgrade_Firestaff_FlameThrower_Dmg.BaseDamage * 100]}":	"50",
  "{[StatusEffects.FireStaff_Burnout_DOT.HealthModifierDamageBased * -100]}":	"5",
  "{[ManaCosts_Player.56.ManaCost]}":	"35",
  "{[FireMagicAbilityTable.Upgrade_Firestaff_BurnOut_CDR.CooldownTimer * -100]}":	"2",
  "{[FireMagicAbilityTable.Passive_Firestaff_Pyro_DmgOnLow.BaseDamage * 100]}":	"20",
  "{[FireMagicAbilityTable.Passive_Firestaff_Pyro_ManaOnblock.Mana * 100]}":	"5",
  "{[StatusEffects.Status_Passive_Firestaff_Pyro_FortOnBurn.ABSStandard * 100]}":	"30",
  "{[StatusEffects.Status_Passive_Firestaff_Pyro_FortOnBurn.BaseDuration]}":	"2",
  "{[FireMagicAbilityTable.Passive_Firestaff_Pyro_ManaOnBurn.TargetStatusEffectDurationMod * 100]}":	"20",
  "{[StatusEffects.Status_Passive_Firestaff_Pyro_BurnNearby.HealthModifierDamageBased * -100]}":	"5",
  "{[StatusEffects.TrialByFireTimer.BaseDuration]}":	"120",
  "{[StatusEffects.Status_Passive_Firestaff_Pyro_Haste.MoveSpeedMod * 100]}":	"20",
  "{[StatusEffects.Status_Passive_Firestaff_Pyro_Haste.BaseDuration]}":	"5",
  "{[StatusEffects.Status_Passive_Firestaff_Pyro_Haste_Timer.BaseDuration]}":	"10",
  "{[StatusEffects.Status_Passive_Firestaff_Pyro_Ultimate_Timer.BaseDuration]}":	"5",
  "{[StatusEffects.Status_Passive_Firestaff_Pyro_Ultimate.ManaRate * 100]}":	"500"
}